deepse/__init__.py
deepse/bert_embedding.py
deepse/simcse.py
deepse/simcse_client.py
deepse/simcse_dataset.py
tests/__init__.py
tests/bert_embedding_test.py
tests/simcse_client_test.py
tests/simcse_dataset_test.py
tests/simcse_test.py
deepse-0.0.4.dist-info/LICENSE
deepse-0.0.4.dist-info/METADATA
deepse-0.0.4.dist-info/WHEEL
deepse-0.0.4.dist-info/top_level.txt
deepse-0.0.4.dist-info/RECORD
