Metadata-Version: 2.1
Name: deepse
Version: 0.0.4
Summary: **DeepSE**: **Sentence Embeddings** based on Deep Nerual Networks, designed for **PRODUCTION** enviroment!
Home-page: https://github.com/luozhouyang/deepse
Author: ZhouYang Luo
Author-email: zhouyang.luo@gmail.com
License: Apache Software License
Platform: UNKNOWN
Classifier: Programming Language :: Python :: 3
Classifier: Programming Language :: Python :: 3.5
Classifier: Programming Language :: Python :: 3.6
Classifier: Programming Language :: Python :: 3.7
Classifier: Programming Language :: Python :: 3.8
Classifier: License :: OSI Approved :: Apache Software License
Classifier: Operating System :: OS Independent
Classifier: Topic :: Scientific/Engineering :: Artificial Intelligence
Requires-Dist: tensorflow
Requires-Dist: transformers-keras (==0.3.1)
Requires-Dist: tokenizers
